[
    {"id":"3845","terrestrial_date":"2024-01-15","sol":"4068","ls":"181","season":"Month 7","min_temp":"-75","max_temp":"-6","pressure":"719","pressure_string":"Lower","abs_humidity":"--","wind_speed":"--","wind_direction":"--","atmo_opacity":"Sunny","sunrise":"05:19","sunset":"17:20","local_uv_irradiance_index":"High","min_gts_temp":"-79","max_gts_temp":"14"},{"id":"3844","terrestrial_date":"2024-01-14","sol":"4067","ls":"181","season":"Month 7","min_temp":"-71","max_temp":"2","pressure":"718","pressure_string":"Lower","abs_humidity":"--","wind_speed":"--","wind_direction":"--","atmo_opacity":"Sunny","sunrise":"05:20","sunset":"17:20","local_uv_irradiance_index":"Moderate","min_gts_temp":"-78","max_gts_temp":"11"},{"id":"3840","terrestrial_date":"2024-01-13","sol":"4066","ls":"180","season":"Month 7","min_temp":"-73","max_temp":"1","pressure":"717","pressure_string":"Lower","abs_humidity":"--","wind_speed":"--","wind_direction":"--","atmo_opacity":"Sunny","sunrise":"05:20","sunset":"17:20","local_uv_irradiance_index":"Moderate","min_gts_temp":"-84","max_gts_temp":"11"},{"id":"3843","terrestrial_date":"2024-01-12","sol":"4065","ls":"179","season":"Month 6","min_temp":"-71","max_temp":"1","pressure":"715","pressure_string":"Lower","abs_humidity":"--","wind_speed":"--","wind_direction":"--","atmo_opacity":"Sunny","sunrise":"05:20","sunset":"17:20","local_uv_irradiance_index":"Moderate","min_gts_temp":"-83","max_gts_temp":"12"},{"id":"3842","terrestrial_date":"2024-01-11","sol":"4064","ls":"179","season":"Month 6","min_temp":"-70","max_temp":"3","pressure":"713","pressure_string":"Lower","abs_humidity":"--","wind_speed":"--","wind_direction":"--","atmo_opacity":"Sunny","sunrise":"05:20","sunset":"17:20","local_uv_irradiance_index":"Moderate","min_gts_temp":"-84","max_gts_temp":"10"},{"id":"3841","terrestrial_date":"2024-01-10","sol":"4063","ls":"178","season":"Month 6","min_temp":"-71","max_temp":"0","pressure":"713","pressure_string":"Lower","abs_humidity":"--","wind_speed":"--","wind_direction":"--","atmo_opacity":"Sunny","sunrise":"05:20","sunset":"17:20","local_uv_irradiance_index":"Moderate","min_gts_temp":"-78","max_gts_temp":"11"},{"id":"3838","terrestrial_date":"2024-01-09","sol":"4062","ls":"178","season":"Month 6","min_temp":"-70","max_temp":"0","pressure":"712","pressure_string":"Lower","abs_humidity":"--","wind_speed":"--","wind_direction":"--","atmo_opacity":"Sunny","sunrise":"05:20","sunset":"17:20","local_uv_irradiance_index":"Moderate","min_gts_temp":"-78","max_gts_temp":"14"},{"id":"3839","terrestrial_date":"2024-01-08","sol":"4061","ls":"177","season":"Month 6","min_temp":"-72","max_temp":"-5","pressure":"712","pressure_string":"Lower","abs_humidity":"--","wind_speed":"--","wind_direction":"--","atmo_opacity":"Sunny","sunrise":"05:20","sunset":"17:20","local_uv_irradiance_index":"Moderate","min_gts_temp":"-84","max_gts_temp":"13"}
]